{
  "_class": "bitmap",
  "booleanOperation": -1,
  "clippingMask": "{{0, 0}, {1, 1}}",
  "clippingMaskMode": 0,
  "do_objectID": "6F57A04D-CF48-48FF-8652-6FCAE831E460",
  "exportOptions": {
    "_class": "exportOptions",
    "do_objectID": "4A904848-CD35-47FE-A1E8-A060D706CF01",
    "exportFormats": [
    ],
    "includedLayerIds": [
    ],
    "layerOptions": 0,
    "shouldTrim": false
  },
  "fillReplacesImage": false,
  "frame": {
    "_class": "rect",
    "constrainProportions": true,
    "do_objectID": "57E5DAB7-3414-46F6-AB8F-7B103A882250",
    "height": 106,
    "width": 1435,
    "x": 0,
    "y": 40
  },
  "hasClippingMask": false,
  "image": {
    "_class": "MSJSONFileReference",
    "_ref": "images/b2d097c9f9b619f5a47afe4e770bfe8cd9403cbb.png",
    "_ref_class": "MSImageData"
  },
  "intendedDPI": 72,
  "isFixedToViewport": false,
  "isFlippedHorizontal": false,
  "isFlippedVertical": false,
  "isLocked": true,
  "isVisible": true,
  "layerListExpandedType": 0,
  "name": "Links 3",
  "nameIsFixed": false,
  "resizingConstraint": 63,
  "resizingType": 0,
  "rotation": 0,
  "shouldBreakMaskChain": false,
  "style": {
    "_class": "style",
    "do_objectID": "123C92E4-6329-4E07-A1A2-24BD7FF2AE8C",
    "endMarkerType": 0,
    "miterLimit": 10,
    "startMarkerType": 0,
    "windingRule": 1
  }
}